formsg/__init__.py
formsg/constants.py
formsg/crypto.py
formsg/exceptions.py
formsg/schemas/__init__.py
formsg/schemas/crypto.py
formsg/schemas/verification.py
formsg/sdk.py
formsg/util/__init__.py
formsg/util/crypto.py
formsg/util/parser.py
formsg/util/validate.py
formsg/util/verification.py
formsg/util/webhook.py
formsg/verification.py
formsg/webhook.py
formsg_python_sdk-0.1.12.dist-info/WHEEL
formsg_python_sdk-0.1.12.dist-info/METADATA
formsg_python_sdk-0.1.12.dist-info/RECORD
