Metadata-Version: 2.1
Name: formsg-python-sdk
Version: 0.1.12
Summary: Python SDK for FormSG
License: MIT
Author: Chin Ying
Author-email: chinying@open.gov.sg
Requires-Python: >=3.6.2,<4.0.0
Classifier: License :: OSI Approved :: MIT License
Classifier: Programming Language :: Python :: 3
Classifier: Programming Language :: Python :: 3.10
Classifier: Programming Language :: Python :: 3.7
Classifier: Programming Language :: Python :: 3.8
Classifier: Programming Language :: Python :: 3.9
Requires-Dist: PyNaCl (>=1.5.0,<2.0.0)
Requires-Dist: pytest (>=6.2.5,<7.0.0)
Requires-Dist: requests (>=2.27.1,<3.0.0)
Requires-Dist: typing_extensions (>=4.0.0,<5.0.0); python_version < "3.11"
